openeihttp/__init__.py
openeihttp/cache.py
openeihttp/const.py
python_openei-0.2.8.dist-info/METADATA
python_openei-0.2.8.dist-info/WHEEL
python_openei-0.2.8.dist-info/top_level.txt
python_openei-0.2.8.dist-info/RECORD
