Metadata-Version: 2.4
Name: python_openei
Version: 0.2.8
Summary: Python wrapper for OpenEI HTTP API
Home-page: https://github.com/firstof9/python-openei
Download-URL: https://github.com/firstof9/python-openei
Author: firstof9
Author-email: firstof9@gmail.com
Classifier: Development Status :: 4 - Beta
Classifier: Intended Audience :: Developers
Classifier: Natural Language :: English
Classifier: Programming Language :: Python :: 3
Classifier: Programming Language :: Python :: 3.9
Classifier: Programming Language :: Python :: 3.10
Requires-Python: >=3.8
Requires-Dist: requests
Dynamic: author
Dynamic: author-email
Dynamic: classifier
Dynamic: description
Dynamic: description-content-type
Dynamic: download-url
Dynamic: home-page
Dynamic: requires-dist
Dynamic: requires-python
Dynamic: summary
